image_to_text/__init__.py
egsimage2text-0.1.dist-info/LICENSE.txt
egsimage2text-0.1.dist-info/METADATA
egsimage2text-0.1.dist-info/WHEEL
egsimage2text-0.1.dist-info/top_level.txt
egsimage2text-0.1.dist-info/RECORD
