Metadata-Version: 2.1
Name: egsimage2text
Version: 0.1
Summary: Image to text convertion package
Home-page: UNKNOWN
Author: srinivasan_rd
Author-email: srinivasan.r.d@egrovesys.com
License: UNKNOWN
Keywords: imagetotext,image to text,OCR,image to text convertion,egs ocr
Platform: UNKNOWN
Classifier: Programming Language :: Python :: 3
Classifier: License :: OSI Approved :: MIT License
Classifier: Operating System :: OS Independent
Requires-Dist: requests
